tut/__init__.py
tut/cmd.py
tut/diff.py
tut/model.py
tut/sphinx/__init__.py
tut/sphinx/checkpoint.py
tut/sphinx/code.py
tut/sphinx/content.py
tut/sphinx/manager.py
tut/tests/__init__.py
tut/tests/test_diffs.py
tut/tests/test_model.py
tut/tests/test_sphinx.py
tut/tests/test_sphinx_code.py
tut-0.5.1.dist-info/DESCRIPTION.rst
tut-0.5.1.dist-info/METADATA
tut-0.5.1.dist-info/RECORD
tut-0.5.1.dist-info/WHEEL
tut-0.5.1.dist-info/entry_points.txt
tut-0.5.1.dist-info/metadata.json
tut-0.5.1.dist-info/top_level.txt
