Metadata-Version: 2.0
Name: tut
Version: 0.5.1
Summary: UNKNOWN
Home-page: http://github.com/nyergler/tut
Author: Nathan Yergler
Author-email: nathan@yergler.net
License: BSD
Platform: UNKNOWN
Requires-Dist: Sphinx
Requires-Dist: docopt
Requires-Dist: pyyaml
Requires-Dist: sh
Requires-Dist: sphinxcontrib-websupport
